{
  "lastUpdate": "2026-05-18 12:20",
  "flashNews": [
    "🔴 5/18 12:25 A古反包｜沪指4160.17+1.17%反共识涨!｜伊朗准备打击纽约/华盛顿ICBM计划｜伊朗浓缩440KG铀"
  ],
  "shipCount": 4,
  "shipChg": "0",
  "oilWti": 103.16,
  "oilWtiChg": "+2.12%",
  "oilWtiNote": "up",
  "goldPrice": 4549.9,
  "goldChg": "-0.26%",
  "goldNote": "down",
  "congestion": 5,
  "congestionNote": "卡塔尔LNG船战后首次通过霍峡｜伊朗选择性放行",
  "barData": [
    {
      "date": "4/20",
      "totalH": 3,
      "oilH": 0,
      "latest": false,
      "count": 3
    },
    {
      "date": "4/21",
      "oilH": 0,
      "totalH": 3,
      "count": 3,
      "latest": false
    },
    {
      "date": "4/22",
      "oilH": 2,
      "totalH": 5,
      "count": 5,
      "latest": false
    },
    {
      "date": "4/23",
      "totalH": 3,
      "oilH": 2,
      "count": 3,
      "latest": false
    },
    {
      "date": "4/24",
      "totalH": 4,
      "oilH": 1,
      "latest": false,
      "count": 4
    },
    {
      "date": "4/25",
      "totalH": 5,
      "oilH": 4,
      "count": 5,
      "latest": false
    },
    {
      "date": "4/26",
      "totalH": 3,
      "oilH": 2,
      "count": 3,
      "latest": false
    },
    {
      "date": "4/27",
      "totalH": 3,
      "oilH": 1,
      "count": 2,
      "latest": false
    },
    {
      "date": "4/28",
      "count": 4,
      "latest": false,
      "totalH": 4,
      "oilH": 2
    },
    {
      "date": "4/29",
      "count": 4,
      "latest": false,
      "totalH": 4,
      "oilH": 2
    },
    {
      "date": "4/30",
      "count": 4,
      "shipChg": "0",
      "latest": false
    },
    {
      "date": "5/1",
      "count": 4,
      "shipChg": "0",
      "latest": false
    },
    {
      "date": "5/2",
      "count": 4,
      "shipChg": "0",
      "latest": false
    },
    {
      "date": "5/3",
      "count": 13,
      "shipChg": "+9",
      "latest": false
    },
    {
      "date": "5/4",
      "count": 2,
      "shipChg": "-11",
      "latest": false
    },
    {
      "date": "5/5",
      "count": 4,
      "shipChg": "+2",
      "latest": false
    },
    {
      "date": "5/6",
      "count": 4,
      "shipChg": "0",
      "latest": false
    },
    {
      "date": "5/7",
      "count": 4,
      "shipChg": "0",
      "latest": false
    },
    {
      "date": "5/9",
      "totalH": 4,
      "oilH": 3,
      "count": 4,
      "latest": false
    },
    {
      "date": "5/10",
      "totalH": 4,
      "oilH": 3,
      "count": 4,
      "latest": false
    },
    {
      "date": "5/11",
      "totalH": 4,
      "oilH": 3,
      "count": 4,
      "latest": false
    },
    {
      "date": "5/14",
      "count": 4,
      "shipChg": "0",
      "latest": false
    },
    {
      "date": "5/11",
      "totalH": 4,
      "oilH": 3,
      "count": 4,
      "latest": false
    },
    {
      "date": "5/12",
      "totalH": 4,
      "oilH": 3,
      "count": 4,
      "latest": false
    },
    {
      "date": "5/13",
      "totalH": 4,
      "oilH": 3,
      "count": 4,
      "latest": false
    },
    {
      "date": "5/14",
      "totalH": 4,
      "oilH": 3,
      "count": 4,
      "latest": false
    },
    {
      "date": "5/15",
      "totalH": 4,
      "oilH": 3,
      "count": 4,
      "latest": false
    },
    {
      "date": "5/16",
      "totalH": 4,
      "oilH": 3,
      "count": 4,
      "latest": false
    },
    {
      "date": "5/17",
      "totalH": 4,
      "oilH": 3,
      "count": 4,
      "latest": false
    },
    {
      "date": "5/18",
      "totalH": 4,
      "oilH": 3,
      "count": 4,
      "latest": true
    }
  ],
  "tableRows": [
    {
      "week": "5/5",
      "count": 4,
      "warDir": "up",
      "warChg": "+2",
      "pct": "3.0%",
      "trend": "up"
    },
    {
      "week": "5/6",
      "count": 4,
      "warDir": "flat",
      "warChg": "0",
      "pct": "3.0%",
      "trend": "flat"
    },
    {
      "week": "5/7",
      "count": 4,
      "warDir": "flat",
      "warChg": "0",
      "pct": "3.0%",
      "trend": "flat"
    },
    {
      "week": "5/9",
      "count": 4,
      "warDir": "flat",
      "warChg": "0",
      "pct": "3.0%",
      "trend": "flat"
    },
    {
      "week": "5/10",
      "count": 4,
      "warDir": "flat",
      "warChg": "0",
      "pct": "3.0%",
      "trend": "flat"
    },
    {
      "week": "5/11",
      "count": 4,
      "warDir": "flat",
      "warChg": "0",
      "pct": "3.0%",
      "trend": "flat"
    },
    {
      "week": "5/14",
      "count": 4,
      "warDir": "flat",
      "warChg": "0",
      "pct": "3.0%",
      "trend": "flat"
    },
    {
      "week": "5/11",
      "count": 4,
      "warDir": "flat",
      "warChg": "0",
      "pct": "3.0%",
      "trend": "flat"
    },
    {
      "week": "5/12",
      "count": 4,
      "warDir": "flat",
      "warChg": "0",
      "pct": "3.0%",
      "trend": "flat"
    },
    {
      "week": "5/13",
      "count": 4,
      "warDir": "flat",
      "warChg": "0",
      "pct": "3.0%",
      "trend": "flat"
    },
    {
      "week": "5/14",
      "count": 4,
      "warDir": "flat",
      "warChg": "0",
      "pct": "3.0%",
      "trend": "flat"
    },
    {
      "week": "5/15",
      "count": 4,
      "warDir": "flat",
      "warChg": "0",
      "pct": "3.0%",
      "trend": "flat"
    },
    {
      "week": "5/16",
      "count": 4,
      "warDir": "flat",
      "warChg": "0",
      "pct": "3.0%",
      "trend": "flat"
    },
    {
      "week": "5/17",
      "count": 4,
      "warDir": "flat",
      "warChg": "0",
      "pct": "3.0%",
      "trend": "flat"
    },
    {
      "week": "● 5/18",
      "count": 4,
      "warDir": "flat",
      "warChg": "0",
      "pct": "3.0%",
      "trend": "flat"
    }
  ],
  "events": [
    {
      "date": "5/18",
      "title": "搜狐实锤:沪指4160.17+1.17%+48.01,A古反共识涨完全打破跳空低开预判"
    },
    {
      "date": "5/18",
      "title": "Yahoo实锤:今日波幅4114.09-4191.81,开盘4174.17高位震荡为主"
    },
    {
      "date": "5/18",
      "title": "YouTube核武级升级:伊朗准备打击纽约/华盛顿大型ICBM计划"
    },
    {
      "date": "5/18",
      "title": "伊朗已浓缩440公斤铀,美国情报与川子矛盾,伊朗导弹网基本完好"
    },
    {
      "date": "5/18",
      "title": "9news官方:UAE Barakah核电站无人机袭击动摇伊朗战争停火"
    },
    {
      "date": "5/18",
      "title": "Aljazeera川子:对伊朗威胁'won't be anything left'谈判停滞"
    }
  ],
  "insightText": "**战后第一艘LNG船过峡了——这是最大的信号。**  5月10日，一艘卡塔尔液化天然气运输船成功穿越霍尔木兹海峡，这是自战争爆发以来首艘通过的LNG船。巴拿马散货船同日放行。伊朗不是全线解封，是在搞选择性审批——谁遵守伊朗新规，谁才能过。  嘴上谈不拢，手上在松闸。这个动作比任何谈判声明都值钱。  同日，川子飞进北京，今天见习近平。议程核心：让中国压伊朗让步，推动霍尔木兹正式解封。美国人自己承认了，锁钥匙在北京不在伊朗。  WTI回落至$95.42，黄金$4715横盘。市场已经开始定价解封预期，但时间线不明确之前，不会一步到位。  封锁第34天，shipCount=4不变。LNG松动是第一块砖。  供参考。",
  "insightTime": "5/14 08:30 · 进度条",
  "shipCountNews": 3,
  "shipChgNews": "0",
  "lngStatus": "🟡 部分松动",
  "lngNote": "封锁第34天｜卡塔尔LNG船+巴拿马货船首次过峡｜伊朗选择性放行",
  "oilWtiChgRaw": 2.12,
  "goldChgRaw": -0.26,
  "goldIsRealtime": false,
  "oilIsRealtime": false,
  "isWeekend": false,
  "shipCountYesterday": 4,
  "shipTrend": "flat",
  "updatedAt": "2026-05-18 12:20",
  "level": "L3",
  "blockadeDays": 34,
  "brent": 114.44,
  "brentChg": "+5.80%",
  "blockadeDay": 34,
  "oilChg": "-9.98%",
  "date": "2026-05-14",
  "updated": "2026-05-07T21:19:54Z",
  "wtiPrice": 103.16,
  "wtiChange": "+2.12%",
  "wti": 103.16,
  "goldChange": "-0.26%",
  "goldDir": "down",
  "gold": 4549.9,
  "lastUpdated": "2026-05-18T12:20:07+08:00"
}